ducttape/__init__.py
ducttape/exceptions.py
ducttape/httpsession.py
ducttape/legacy.py
ducttape/utils.py
ducttape/webui_datasource.py
ducttape/data_sources/__init__.py
ducttape/data_sources/clever.py
ducttape/data_sources/googlesheets.py
ducttape/data_sources/informedk12.py
ducttape/data_sources/lexia.py
ducttape/data_sources/mealtime.py
ducttape/data_sources/schoolmint.py
ducttape/data_sources/summitlearning.py
ducttape/data_sources/typingagent.py
duct_tape-0.24.3.dist-info/LICENSE
duct_tape-0.24.3.dist-info/METADATA
duct_tape-0.24.3.dist-info/WHEEL
duct_tape-0.24.3.dist-info/top_level.txt
duct_tape-0.24.3.dist-info/RECORD
