Metadata-Version: 2.1
Name: duct-tape
Version: 0.24.3
Summary: Duct Tape is a Python interface for downloading data, uploading data, and controlling supported Ed-Tech software.
Home-page: https://github.com/SummitPublicSchools/ducttape
Author: Patrick Yoho
Author-email: trickyoho@gmail.com
License: UNKNOWN
Keywords: automation,education,illuminate,selenium,etl
Platform: UNKNOWN
Classifier: License :: OSI Approved :: GNU Lesser General Public License v3 (LGPLv3)
Classifier: Programming Language :: Python :: 2.7
Classifier: Programming Language :: Python :: 3
Classifier: Operating System :: OS Independent
Requires-Dist: psycopg2-binary (>=2.7.1)
Requires-Dist: paramiko (>=2.1.2)
Requires-Dist: beautifulsoup4 (>=4.5.1)
Requires-Dist: numpy
Requires-Dist: selenium (>=3.4.3)
Requires-Dist: requests (>=2.11.1)
Requires-Dist: oauth2client
Requires-Dist: pandas (>=0.20.3)
Requires-Dist: xlrd (>=0.9.0)
Requires-Dist: future (>=0.15.2)
